pbcluster/__init__.py
pbcluster/cluster.py
pbcluster/trajectory.py
pbcluster/utils.py
pbcluster-0.2.1.dist-info/AUTHORS.rst
pbcluster-0.2.1.dist-info/LICENSE
pbcluster-0.2.1.dist-info/METADATA
pbcluster-0.2.1.dist-info/WHEEL
pbcluster-0.2.1.dist-info/top_level.txt
pbcluster-0.2.1.dist-info/RECORD
