Metadata-Version: 2.1
Name: pbcluster
Version: 0.2.1
Summary: Analyze particle clusters in boxes with periodic boundaries
Home-page: https://github.com/benlindsay/pbcluster
Author: Ben Lindsay
Author-email: benjlindsay@gmail.com
License: MIT license
Keywords: pbcluster
Platform: UNKNOWN
Classifier: Development Status :: 2 - Pre-Alpha
Classifier: Intended Audience :: Developers
Classifier: License :: OSI Approved :: MIT License
Classifier: Natural Language :: English
Classifier: Programming Language :: Python :: 3
Classifier: Programming Language :: Python :: 3.6
Classifier: Programming Language :: Python :: 3.7
Requires-Dist: networkx (>=2.1)
Requires-Dist: numpy
Requires-Dist: pandas
Requires-Dist: plotnine
Requires-Dist: scikit-learn
Requires-Dist: scipy
Requires-Dist: pygraphviz
